{
	"games" : [
		{
		    "questions" : [
		        {
		            "question" : "Oque é empreendedorismo?",
		            "content" : [
		                "é o processo de iniciativa de implementar novos negócios ou mudanças em empresas",
		                "é uma empresa de contruções civis",
		                "é o processo de construção de prédios",
		                "é um modelo de banco de dados"
		            ],
		            "correct" : 0
		        },
		      
				{
				    "correct": 2,
				    "content" : [
				        "Robert e Dominick",
				        "Morgan Freeman",
				        "Robbins e Decenzo",
				        "Kelly e Key"
				    ],
				    "Quem escreveu o livro Fundamentos de administração"
				}
		    ]
		}
	]
}
